python_practice_algorithm_pack/__init__.py
python_practice_algorithm_pack/stack.py
python_practice_algorithm_pack-0.1.0.dist-info/METADATA
python_practice_algorithm_pack-0.1.0.dist-info/WHEEL
python_practice_algorithm_pack-0.1.0.dist-info/RECORD
