Metadata-Version: 2.3
Name: python-practice-algorithm-pack
Version: 0.1.0
Summary: A project for practicing python packaging techniques.
Author: Dimitar Stoyanov
Author-email: me@dimitars.dev
Requires-Python: >=3.12
Classifier: Programming Language :: Python :: 3
Classifier: Programming Language :: Python :: 3.12
Classifier: Programming Language :: Python :: 3.13
